jdrones/__init__.py
jdrones/_version.py
jdrones/controllers.py
jdrones/data_models.py
jdrones/energy_model.py
jdrones/maths.py
jdrones/plotting.py
jdrones/solvers.py
jdrones/trajectory.py
jdrones/transforms.py
jdrones/types.py
jdrones/envs/__init__.py
jdrones/envs/drone.dae
jdrones/envs/dronemodels.py
jdrones/envs/droneplus.urdf
jdrones/envs/lqr.py
jdrones/envs/position.py
jdrones/envs/base/__init__.py
jdrones/envs/base/__main__.py
jdrones/envs/base/basecontrolledenv.py
jdrones/envs/base/basedronenev.py
jdrones/envs/base/lineardronenev.py
jdrones/envs/base/nonlineardronenev.py
jdrones-0.10.1.dist-info/METADATA
jdrones-0.10.1.dist-info/WHEEL
jdrones-0.10.1.dist-info/licenses/AUTHORS.md
jdrones-0.10.1.dist-info/licenses/LICENSE.txt
jdrones-0.10.1.dist-info/RECORD
