Metadata-Version: 2.4
Name: jdrones
Version: 0.10.1
Summary: Drones models prepared for use via the gymnasium environment
Project-URL: Homepage, https://github.com/iwishiwasaneagle/jdrones/
Project-URL: Source, https://github.com/iwishiwasaneagle/jdrones
Author-email: iwishiwasaneagle <me@janhendrikewers.uk>
License: GPL-3.0-or-later
License-File: AUTHORS.md
License-File: LICENSE.txt
Classifier: Development Status :: 3 - Alpha
Classifier: License :: OSI Approved :: GNU General Public License v3 or later (GPLv3+)
Classifier: Natural Language :: English
Classifier: Operating System :: Unix
Classifier: Programming Language :: Python :: 3 :: Only
Classifier: Programming Language :: Python :: 3.10
Classifier: Programming Language :: Python :: 3.11
Classifier: Topic :: Scientific/Engineering
Requires-Python: >=3.10
Requires-Dist: gymnasium
Requires-Dist: libjdrones>=0.1.1
Requires-Dist: loguru
Requires-Dist: numba
Requires-Dist: numpy
Requires-Dist: pydantic
Requires-Dist: scipy
Provides-Extra: examples
Requires-Dist: click; extra == 'examples'
Requires-Dist: optuna; extra == 'examples'
Requires-Dist: sb3-contrib; extra == 'examples'
Requires-Dist: sbx-rl; extra == 'examples'
Requires-Dist: tensorboard; extra == 'examples'
Requires-Dist: tensorflow-probability==0.25.0; extra == 'examples'
Requires-Dist: wandb; extra == 'examples'
Provides-Extra: test
Requires-Dist: hypothesis; extra == 'test'
Requires-Dist: pytest; extra == 'test'
Requires-Dist: pytest-cov; extra == 'test'
Requires-Dist: pytest-extra-markers; extra == 'test'
Requires-Dist: pytest-mock; extra == 'test'
Requires-Dist: pytest-xdist; extra == 'test'
